[ {
  "ar" : "بِسْمِ اللَّهِ الرَّحْمَٰنِ الرَّحِيمِ",
  "id" : "Dengan menyebut nama Allah Yang Maha Pemurah lagi Maha Penyayang.",
  "nomor" : "1",
  "tr" : "bismi <strong>al</strong>l<u>aa</u>hi <strong>al</strong>rra<u>h</u>m<u>aa</u>ni <strong>al</strong>rra<u>h</u>iim<strong>i</strong>"
}, {
  "ar" : "الْحَمْدُ لِلَّهِ رَبِّ الْعَالَمِينَ",
  "id" : "Segala puji bagi Allah, Tuhan semesta alam.",
  "nomor" : "2",
  "tr" : "al<u>h</u>amdu lill<u>aa</u>hi rabbi <strong>a</strong>l'<u>aa</u>lamiin<strong>a</strong>"
}, {
  "ar" : "الرَّحْمَٰنِ الرَّحِيمِ",
  "id" : "Maha Pemurah lagi Maha Penyayang.",
  "nomor" : "3",
  "tr" : "a<strong>l</strong>rra<u>h</u>m<u>aa</u>ni <strong>al</strong>rra<u>h</u>iim<strong>i</strong>"
}, {
  "ar" : "مَالِكِ يَوْمِ الدِّينِ",
  "id" : "Yang menguasai di Hari Pembalasan",
  "nomor" : "4",
  "tr" : "m<u>aa</u>liki yawmi <strong>al</strong>ddiin<strong>i</strong>"
}, {
  "ar" : "إِيَّاكَ نَعْبُدُ وَإِيَّاكَ نَسْتَعِينُ",
  "id" : "Hanya Engkaulah yang kami sembah, dan hanya kepada Engkaulah kami meminta pertolongan.",
  "nomor" : "5",
  "tr" : "iyy<u>aa</u>ka na'budu wa-iyy<u>aa</u>ka nasta'iin<strong>u</strong>"
}, {
  "ar" : "اهْدِنَا الصِّرَاطَ الْمُسْتَقِيمَ",
  "id" : "Tunjukilah kami jalan yang lurus,",
  "nomor" : "6",
  "tr" : "ihdin<u>aa</u> <strong>al</strong><u>shsh</u>ir<u>aath</u>a <strong>a</strong>lmustaqiim<strong>a</strong>"
}, {
  "ar" : "صِرَاطَ الَّذِينَ أَنْعَمْتَ عَلَيْهِمْ غَيْرِ الْمَغْضُوبِ عَلَيْهِمْ وَلَا الضَّالِّينَ",
  "id" : "(yaitu) Jalan orang-orang yang telah Engkau beri ni'mat kepada mereka; bukan (jalan) mereka yang dimurkai dan bukan (pula jalan) mereka yang sesat.",
  "nomor" : "7",
  "tr" : "<u>sh</u>ir<u>aath</u>a <strong>al</strong>la<u>dz</u>iina an'amta 'alayhim ghayri <strong>a</strong>lmagh<u>dh</u>uubi 'alayhim wal<u>aa</u> <strong>al</strong><u>dhdhaa</u>lliin<strong>a</strong>"
} ]
